spdxmerge/SPDXMerge.py
spdxmerge/SPDXMergeLib.py
spdxmerge/SPDX_DeepMerge.py
spdxmerge/SPDX_ShallowMerge.py
spdxmerge/__init__.py
spdxmerge/checksum.py
spdxmerge/utils.py
spdxmerge-0.2.0.dist-info/LICENSE
spdxmerge-0.2.0.dist-info/METADATA
spdxmerge-0.2.0.dist-info/WHEEL
spdxmerge-0.2.0.dist-info/entry_points.txt
spdxmerge-0.2.0.dist-info/top_level.txt
spdxmerge-0.2.0.dist-info/RECORD
