Metadata-Version: 2.1
Name: spdxmerge
Version: 0.2.0
Summary: merges content of two/more spdx sboms
Home-page: https://github.com/philips-software/SPDXMerge
Classifier: Programming Language :: Python :: 3
Classifier: License :: OSI Approved :: MIT License
Classifier: Operating System :: OS Independent
Requires-Python: >=3.8
License-File: LICENSE
Requires-Dist: spdx-tools (==0.7.1)
Requires-Dist: click (==8.1.3)
